lazy/__init__.py
lazy/extract.py
extract_6a6f6a6f-1.0.0.dist-info/LICENSE.txt
extract_6a6f6a6f-1.0.0.dist-info/METADATA
extract_6a6f6a6f-1.0.0.dist-info/WHEEL
extract_6a6f6a6f-1.0.0.dist-info/entry_points.txt
extract_6a6f6a6f-1.0.0.dist-info/top_level.txt
extract_6a6f6a6f-1.0.0.dist-info/RECORD
