Metadata-Version: 2.1
Name: extract-6a6f6a6f
Version: 1.0.0
Summary: Just pull an application from an Android device
Home-page: https://github.com/zone016/lazy-android-app-extraction
Author: Jonas (Jojo) Uliana
Author-email: jonas.uliana@passwd.com.br
License: MIT
Project-URL: Bug Tracker, https://github.com/zone016/lazy-android-app-extraction/issues
Keywords: android,extract
Platform: UNKNOWN
Classifier: Development Status :: 5 - Production/Stable
Classifier: Intended Audience :: Developers
Classifier: Topic :: Software Development
Classifier: License :: OSI Approved :: MIT License
Classifier: Operating System :: OS Independent
Requires-Python: >=3.6
License-File: LICENSE.txt
Requires-Dist: colorama (~=0.4.4)
Requires-Dist: termcolor (~=1.1.0)
